justdoit/__init__.py
justdoit-1.0.0.dist-info/METADATA
justdoit-1.0.0.dist-info/WHEEL
justdoit-1.0.0.dist-info/licenses/LICENSE.md
justdoit-1.0.0.dist-info/RECORD
