Metadata-Version: 2.3
Name: justdoit
Version: 1.0.0
Summary: Prints out the immortal motivational meme of 'Just Do It'
Project-URL: Repository, https://github.com/cmsato09/justdoit
Project-URL: Issues, https://github.com/cmsato09/justdoit/issues
Author-email: Chris Sato <chrismsato@gmail.com>
License-File: LICENSE.md
Keywords: import this,just do it,motivation
Classifier: License :: OSI Approved :: MIT License
Classifier: Operating System :: OS Independent
Classifier: Programming Language :: Python :: 3
Requires-Python: >=3.8
